AlignMolecule/__init__.py
ovitocontrib_AlignMolecule-2024.5.dist-info/LICENSE
ovitocontrib_AlignMolecule-2024.5.dist-info/METADATA
ovitocontrib_AlignMolecule-2024.5.dist-info/WHEEL
ovitocontrib_AlignMolecule-2024.5.dist-info/entry_points.txt
ovitocontrib_AlignMolecule-2024.5.dist-info/top_level.txt
ovitocontrib_AlignMolecule-2024.5.dist-info/RECORD
