Metadata-Version: 2.1
Name: ovitocontrib-AlignMolecule
Version: 2024.5
Summary: Align molecules using the Kabsch algorithm.
Author-email: Daniel Utt <utt@ovito.org>
Maintainer-email: Daniel Utt <utt@ovito.org>
License: MIT
Project-URL: repository, https://github.com/ovito-org/AlignMolecule
Keywords: ovito,ovito-extension
Requires-Python: >=3.7
License-File: LICENSE
Requires-Dist: ovito>=3.9.1
